.gitignore
LICENSE.txt
README.rst
setup.cfg
setup.py
PKGBUILD/PKGBUILD
jutge_cli/__init__.py
jutge_cli/jutge.py
jutge_cli.egg-info/PKG-INFO
jutge_cli.egg-info/SOURCES.txt
jutge_cli.egg-info/dependency_links.txt
jutge_cli.egg-info/entry_points.txt
jutge_cli.egg-info/requires.txt
jutge_cli.egg-info/top_level.txt
jutge_cli.egg-info/zip-safe
jutge_cli/commands/__init__.py
jutge_cli/commands/add_test.py
jutge_cli/commands/archive.py
jutge_cli/commands/check_submissions.py
jutge_cli/commands/cookie.py
jutge_cli/commands/defaults.py
jutge_cli/commands/download.py
jutge_cli/commands/get_code.py
jutge_cli/commands/import_zip.py
jutge_cli/commands/login.py
jutge_cli/commands/new.py
jutge_cli/commands/show.py
jutge_cli/commands/test.py
jutge_cli/commands/upload.py
zsh_completion/_jutge