Metadata-Version: 1.1
Name: jutge-cli
Version: 2.1.11
Summary: CLI to automate tests for jutge.org problems
Home-page: http://github.com/Leixb/jutge_cli
Author: Aleix Boné (Leix_b)
Author-email: abone9999@gmail.com
License: GPL3
Keywords: jutge jutge.org jutge_cli
Platform: UNKNOWN
Classifier: Development Status :: 4 - Beta
Classifier: Environment :: Console
Classifier: Intended Audience :: Education
Classifier: License :: OSI Approved :: GNU General Public License v3 (GPLv3)
Classifier: Programming Language :: Python :: 3 :: Only
Classifier: Topic :: Education
